CubeFlow-0.1.7.dist-info/DESCRIPTION.rst
CubeFlow-0.1.7.dist-info/METADATA
CubeFlow-0.1.7.dist-info/RECORD
CubeFlow-0.1.7.dist-info/WHEEL
CubeFlow-0.1.7.dist-info/metadata.json
CubeFlow-0.1.7.dist-info/top_level.txt
cubeflow/__init__.py
cubeflow/cell.py
cubeflow/cube.py
cubeflow/logging.py
cubeflow/math.py
cubeflow/simulator.py
cubeflow/predicates/__init__.py
cubeflow/predicates/counter.py
cubeflow/report/__init__.py
cubeflow/report/csv.py
cubeflow/report/vector.py
