Metadata-Version: 2.0
Name: CubeFlow
Version: 0.1.7
Summary: Framework for creating grid based simulations.
Home-page: https://bitbucket.org/voidpointercast/cubeflow
Author: Patrick Daniel Greß
Author-email: patrick.daniel.gress@gmail.com
License: GPLv3 or later
Keywords: education simulation mathematics physics
Platform: UNKNOWN
Classifier: Development Status :: 3 - Alpha
Classifier: Intended Audience :: Education
Classifier: Intended Audience :: Science/Research
Classifier: License :: OSI Approved :: GNU General Public License v3 or later (GPLv3+)
Classifier: Topic :: Education
Classifier: Topic :: Scientific/Engineering :: Mathematics
Classifier: Topic :: Scientific/Engineering :: Physics
Classifier: Programming Language :: Python :: 3.5
Requires-Dist: grako
Requires-Dist: matplotlib
